nicevk/__init__.py
nicevk/api.py
nicevk/cli.py
nicevk/plugins/help_plugin.py
nicevk/plugins/ignore_plugin.py
nicevk/plugins/load_plugin.py
nicevk/plugins/neofetch_plugin.py
nicevk/plugins/notes_plugin.py
nicevk/plugins/restart_plugin.py
nicevk/plugins/spam_plugin.py
nicevk-0.4.0.dist-info/entry_points.txt
nicevk-0.4.0.dist-info/WHEEL
nicevk-0.4.0.dist-info/METADATA
nicevk-0.4.0.dist-info/RECORD
