Metadata-Version: 2.1
Name: nicevk
Version: 0.4.0
Summary: 
Author: nm17
Author-email: dannevergame@gmail.com
Requires-Python: >=3.8,<4.0
Classifier: Programming Language :: Python :: 3
Classifier: Programming Language :: Python :: 3.8
Requires-Dist: psutil (>=5.7.0,<6.0.0)
Requires-Dist: python-dotenv (>=0.13.0,<0.14.0)
Requires-Dist: vkbottle (>=2.7.2,<3.0.0)
Requires-Dist: wget (>=3.2,<4.0)
